LICENSE.txt
MANIFEST.in
README.md
setup.py
django_web_secure/__init__.py
django_web_secure/middleware.py
django_web_secure/tests.py
django_web_secure.egg-info/PKG-INFO
django_web_secure.egg-info/SOURCES.txt
django_web_secure.egg-info/dependency_links.txt
django_web_secure.egg-info/requires.txt
django_web_secure.egg-info/top_level.txt