Metadata-Version: 1.1
Name: django-web-secure
Version: 0.1
Summary: The middleware that makes ponies fly with a great sense of security.
Home-page: https://github.com/syndbg/django-web-secure
Author: Anton Antonov
Author-email: syndbe@gmail.com
License: MIT
Keywords: pypi django web security secure package
Platform: any
Classifier: Environment :: Web Environment
Classifier: Framework :: Django
Classifier: Intended Audience :: Developers
Classifier: License :: OSI Approved :: MIT License
Classifier: Operating System :: OS Independent
Classifier: Programming Language :: Python
Classifier: Programming Language :: Python :: 3
Classifier: Topic :: Internet :: WWW/HTTP
Classifier: Topic :: Internet :: WWW/HTTP :: Dynamic Content
